[{"model": "RandomForest", "accuracy": 0.8256410256410256, "f1_score": 0.8249667131554125, "metric_type": "transition_forecast", "forecast_horizon_steps": 1, "nowcast_accuracy": 0.9128205128205128, "nowcast_f1_score": 0.9097937795350223, "forecast_proxy_accuracy": 0.8, "forecast_proxy_f1_score": 0.8021429276430222, "transition_forecast_accuracy": 0.8256410256410256, "transition_forecast_f1_score": 0.8249667131554125}, {"model": "XGBoost", "accuracy": 0.8256410256410256, "f1_score": 0.8357354925775978, "metric_type": "transition_forecast", "forecast_horizon_steps": 1, "nowcast_accuracy": 0.9128205128205128, "nowcast_f1_score": 0.923581051716645, "forecast_proxy_accuracy": 0.841025641025641, "forecast_proxy_f1_score": 0.8256626357245552, "transition_forecast_accuracy": 0.8256410256410256, "transition_forecast_f1_score": 0.8357354925775978}, {"model": "Ridge", "accuracy": 0.8307692307692308, "f1_score": 0.7846241330540313, "metric_type": "transition_forecast", "forecast_horizon_steps": 1, "nowcast_accuracy": 0.8461538461538461, "nowcast_f1_score": 0.8012881032011466, "forecast_proxy_accuracy": 0.8153846153846154, "forecast_proxy_f1_score": 0.7721980325753911, "transition_forecast_accuracy": 0.8307692307692308, "transition_forecast_f1_score": 0.7846241330540313}]